MANIFEST.in
README.rst
TITLE.txt
lh-agpl3-LICENSE.txt
setup.py
./bin/csExamples.cs
./bin/csIcmExamples.cs
bisos/__init__.py
bisos.bpf.egg-info/PKG-INFO
bisos.bpf.egg-info/SOURCES.txt
bisos.bpf.egg-info/dependency_links.txt
bisos.bpf.egg-info/namespace_packages.txt
bisos.bpf.egg-info/not-zip-safe
bisos.bpf.egg-info/top_level.txt
bisos/bpf/__init__.py
bisos/bpf/ast.py
bisos/bpf/comment.py
bisos/bpf/copyOfUcf.py
bisos/bpf/copyOf_fpBase.py
bisos/bpf/copyOf_fpIcm.py
bisos/bpf/copyOf_icm.py
bisos/bpf/dir.py
bisos/bpf/exception.py
bisos/bpf/fp.py
bisos/bpf/fto.py
bisos/bpf/fv.py
bisos/bpf/niche.py
bisos/bpf/op.py
bisos/bpf/pyRunAs.py
bisos/bpf/shIcm.py
bisos/bpf/subProc.py
bisos/bpf/types.py